ansys/scade/guitools/__init__.py
ansys/scade/guitools/command.py
ansys/scade/guitools/control.py
ansys/scade/guitools/csts.py
ansys/scade/guitools/data.py
ansys/scade/guitools/dialog.py
ansys/scade/guitools/enable_debugpy.py
ansys/scade/guitools/guihost.py
ansys/scade/guitools/guitools.srg
ansys/scade/guitools/guitools23r1.srg
ansys/scade/guitools/guitools24r1.srg
ansys/scade/guitools/ide.py
ansys/scade/guitools/interfaces.py
ansys/scade/guitools/page.py
ansys/scade/guitools/register.py
ansys/scade/guitools/stubs.py
ansys/scade/guitools/studio.py
ansys/scade/guitools/studio_ext.py
ansys/scade/guitools/unregister.py
ansys_scade_guitools-2.3.4.dist-info/entry_points.txt
ansys_scade_guitools-2.3.4.dist-info/licenses/LICENSE
ansys_scade_guitools-2.3.4.dist-info/WHEEL
ansys_scade_guitools-2.3.4.dist-info/METADATA
ansys_scade_guitools-2.3.4.dist-info/RECORD
