Metadata-Version: 2.4
Name: ansys-scade-guitools
Version: 2.3.4
Summary: Python library for extending the Ansys SCADE IDE GUI.
Keywords: Scade,IDE,GUI,Dialog,Menu,Toolbar,Page,Settings,Properties
Author-email: "ANSYS, Inc." <pyansys.core@ansys.com>
Maintainer-email: "ANSYS, Inc." <pyansys.core@ansys.com>
Requires-Python: >=3.7,!=3.8.*,!=3.9.*,!=3.11
License-Expression: MIT
Classifier: Development Status :: 4 - Beta
Classifier: Intended Audience :: Developers
Classifier: Intended Audience :: Science/Research
Classifier: Topic :: Software Development :: Embedded Systems
Classifier: Programming Language :: Python :: 3.7
Classifier: Programming Language :: Python :: 3.10
Classifier: Operating System :: Microsoft :: Windows
License-File: LICENSE
Requires-Dist: importlib-metadata >= 1.0; python_version < '3.8'
Requires-Dist: importlib-metadata >= 4.0; python_version >= '3.8'
Requires-Dist: ansys.scade.apitools >= 0.5.0
Requires-Dist: build==1.3.0 ; extra == "build"
Requires-Dist: twine==6.2.0 ; extra == "build"
Requires-Dist: ansys-sphinx-theme[autoapi]==1.5.2 ; extra == "doc"
Requires-Dist: autodoc_pydantic==2.2.0 ; extra == "doc"
Requires-Dist: jupyter_sphinx==0.5.3 ; extra == "doc"
Requires-Dist: nbsphinx==0.9.7 ; extra == "doc"
Requires-Dist: numpydoc==1.9.0 ; extra == "doc"
Requires-Dist: sphinx==8.1.3 ; extra == "doc"
Requires-Dist: sphinx-autoapi<=3.6.1 ; extra == "doc"
Requires-Dist: sphinx-autodoc-typehints==3.0.1 ; extra == "doc"
Requires-Dist: sphinxcontrib-globalsubs==0.1.2 ; extra == "doc"
Requires-Dist: sphinxcontrib-httpdomain==1.8.1 ; extra == "doc"
Requires-Dist: sphinx-copybutton==0.5.2 ; extra == "doc"
Requires-Dist: sphinx-jinja==2.0.2 ; extra == "doc"
Requires-Dist: sphinxnotes-strike==1.2.1 ; extra == "doc"
Requires-Dist: pytest >= 9.0.1 ; extra == "tests" and ( python_version >= '3.8')
Requires-Dist: pytest <= 7.4.4 ; extra == "tests" and ( python_version < '3.8')
Requires-Dist: pytest-cov >= 6.0.0 ; extra == "tests" and ( python_version >= '3.8')
Requires-Dist: pytest-cov <= 4.1.0 ; extra == "tests" and ( python_version < '3.8')
Requires-Dist: debugpy ; extra == "tests"
Project-URL: Discussions, https://github.com/ansys/scade-guitools/discussions
Project-URL: Documentation, https://guitools.scade.docs.pyansys.com
Project-URL: Homepage, https://www.ansys.com/products/embedded-software/ansys-scade-suite
Project-URL: Issues, https://github.com/ansys/scade-guitools/issues
Project-URL: Releases, https://github.com/ansys/scade-guitools/releases
Project-URL: Source, https://github.com/ansys/scade-guitools
Provides-Extra: build
Provides-Extra: doc
Provides-Extra: tests
